[{"pk": 1, "model": "analytics.category", "fields": {"enabled": true, "name": "Engagement", "slug": "engagement"}}, {"pk": 2, "model": "analytics.category", "fields": {"enabled": true, "name": "Sharing", "slug": "sharing"}}, {"pk": 3, "model": "analytics.category", "fields": {"enabled": true, "name": "Awareness", "slug": "awareness"}}, {"pk": 1, "model": "analytics.metric", "fields": {"data": [], "enabled": true, "name": "Total Interactions", "slug": "total-interactions"}}, {"pk": 2, "model": "analytics.metric", "fields": {"data": [], "enabled": true, "name": "Open Preview Popup", "slug": "inpage-openpopup"}}, {"pk": 3, "model": "analytics.metric", "fields": {"data": [], "enabled": true, "name": "Shared (Started to Post)", "slug": "share-clicked"}}, {"pk": 4, "model": "analytics.metric", "fields": {"data": [], "enabled": true, "name": "Shared (Posted)", "slug": "share-shared"}}, {"pk": 5, "model": "analytics.metric", "fields": {"data": [], "enabled": true, "name": "Total Shares", "slug": "total-shares"}}, {"pk": 6, "model": "analytics.metric", "fields": {"data": [], "enabled": true, "name": "Product Interactions", "slug": "product-interactions"}}, {"pk": 7, "model": "analytics.metric", "fields": {"data": [], "enabled": true, "name": "Content Interactions", "slug": "content-interactions"}}, {"pk": 8, "model": "analytics.metric", "fields": {"data": [], "enabled": true, "name": "Total Visitors", "slug": "awareness-visitors"}}, {"pk": 9, "model": "analytics.metric", "fields": {"data": [], "enabled": true, "name": "Total Pageviews", "slug": "awareness-pageviews"}}, {"pk": 11, "model": "analytics.metric", "fields": {"data": [], "enabled": true, "name": "Not a Bounce", "slug": "visit-noBounce"}}, {"pk": 12, "model": "analytics.metric", "fields": {"data": [], "enabled": true, "name": "Total No Bounces", "slug": "total-no-bounces"}}, {"pk": 13, "model": "analytics.metric", "fields": {"data": [], "enabled": true, "name": "Liked", "slug": "share-liked"}}, {"pk": 14, "model": "analytics.metric", "fields": {"data": [], "enabled": true, "name": "Product Hover", "slug": "inpage-hover"}}, {"pk": 4, "model": "analytics.categoryhasmetric", "fields": {"category": 1, "metric": 1, "order": 3, "display": true}}, {"pk": 2, "model": "analytics.categoryhasmetric", "fields": {"category": 1, "metric": 6, "order": 2, "display": true}}, {"pk": 8, "model": "analytics.categoryhasmetric", "fields": {"category": 3, "metric": 8, "order": 2, "display": true}}, {"pk": 3, "model": "analytics.categoryhasmetric", "fields": {"category": 1, "metric": 7, "order": 1, "display": true}}, {"pk": 9, "model": "analytics.categoryhasmetric", "fields": {"category": 3, "metric": 9, "order": 1, "display": true}}, {"pk": 1, "model": "analytics.categoryhasmetric", "fields": {"category": 1, "metric": 2, "order": 0, "display": false}}, {"pk": 5, "model": "analytics.categoryhasmetric", "fields": {"category": 2, "metric": 3, "order": 0, "display": false}}, {"pk": 6, "model": "analytics.categoryhasmetric", "fields": {"category": 2, "metric": 4, "order": 0, "display": false}}, {"pk": 7, "model": "analytics.categoryhasmetric", "fields": {"category": 2, "metric": 5, "order": 0, "display": true}}, {"pk": 11, "model": "analytics.categoryhasmetric", "fields": {"category": 1, "metric": 11, "order": 0, "display": false}}, {"pk": 12, "model": "analytics.categoryhasmetric", "fields": {"category": 1, "metric": 12, "order": 0, "display": false}}, {"pk": 13, "model": "analytics.categoryhasmetric", "fields": {"category": 2, "metric": 13, "order": 0, "display": false}}, {"pk": 14, "model": "analytics.categoryhasmetric", "fields": {"category": 1, "metric": 14, "order": 0, "display": false}}]